{
  "success": true,
  "unit": {
    "title": "CLOSING PROCEDURES — PRACTICE (Including Cash)",
    "duration": "6-8 hours (2-3 closing shifts)",
    "trainer": "Demetri",
    "location": "",
    "purpose": "",
    "contentSections": [
      {
        "heading": "Step-by-Step Process",
        "content": [
          {
            "type": "paragraph",
            "content": "**1. Open the Safe**"
          },
          {
            "type": "list",
            "items": [
              "Key turned RIGHT",
              "Enter code",
              "Green light → turn knob RIGHT"
            ]
          },
          {
            "type": "paragraph",
            "content": "**2. Remove Cash Materials**"
          },
          {
            "type": "list",
            "items": [
              "Cashbox (hold from BOTTOM—handle not secure)",
              "Bank envelope for current day"
            ]
          },
          {
            "type": "paragraph",
            "content": "**3. Go to Registers**"
          },
          {
            "type": "list",
            "items": [
              "Open Jayna App → CASH → Password: jaynacash",
              "Select your name"
            ]
          },
          {
            "type": "paragraph",
            "content": "**4. Count the Drawers**"
          },
          {
            "type": "list",
            "items": [
              "Start with Drawer #1 (near Turkish delight)",
              "Count by NUMBER of bills/coins (app calculates value)",
              "Repeat for Drawer #2"
            ]
          },
          {
            "type": "paragraph",
            "content": "**5. Review Results**"
          },
          {
            "type": "list",
            "items": [
              "Over $10 discrepancy: RETRY → Recount → Continue and document"
            ]
          },
          {
            "type": "paragraph",
            "content": "**6. Enter Cash Tips & Submit**"
          },
          {
            "type": "list",
            "items": [
              "Enter total cash tips amount",
              "SUBMIT → prints report in office"
            ]
          },
          {
            "type": "paragraph",
            "content": "**7. Prepare Bank Envelope**"
          },
          {
            "type": "list",
            "items": [
              "Fold report neatly",
              "Place exact deposit amount + report in envelope",
              "Seal"
            ]
          },
          {
            "type": "paragraph",
            "content": "**8. Lock Everything Up**"
          },
          {
            "type": "list",
            "items": [
              "Return cashbox and envelope to safe",
              "Knob LEFT, key LEFT"
            ]
          }
        ]
      }
    ],
    "activities": [],
    "fullMarkdown": "# UNIT 2.5: CLOSING PROCEDURES — PRACTICE (Including Cash)\n\n**Duration:** 6-8 hours (2-3 closing shifts)  \n**Trainer:** Demetri\n\n## Cash Handling Procedures\n\n### Step-by-Step Process\n\n**1. Open the Safe**\n- Key turned RIGHT\n- Enter code\n- Green light → turn knob RIGHT\n\n**2. Remove Cash Materials**\n- Cashbox (hold from BOTTOM—handle not secure)\n- Bank envelope for current day\n\n**3. Go to Registers**\n- Open Jayna App → CASH → Password: jaynacash\n- Select your name\n\n**4. Count the Drawers**\n- Start with Drawer #1 (near Turkish delight)\n- Count by NUMBER of bills/coins (app calculates value)\n- Repeat for Drawer #2\n\n**5. Review Results**\n- Over $10 discrepancy: RETRY → Recount → Continue and document\n\n**6. Enter Cash Tips & Submit**\n- Enter total cash tips amount\n- SUBMIT → prints report in office\n\n**7. Prepare Bank Envelope**\n- Fold report neatly\n- Place exact deposit amount + report in envelope\n- Seal\n\n**8. Lock Everything Up**\n- Return cashbox and envelope to safe\n- Knob LEFT, key LEFT\n\n## Practice Shifts\n\n**Shift 1:** Shadow complete closing + watch cash handling  \n**Shift 2:** Execute with supervision (first cash handling guided)  \n**Shift 3:** Execute independently (Demetri reviews next day)\n\n---\n",
    "reflection": [
      "The cash counting process step-by-step",
      "If my cash count is off by more than $10, I will",
      "The cashbox handle is not secure, so I should",
      "The three most commonly missed closing tasks are",
      "My closing time was _______ minutes. The most time-consuming tasks were",
      "One thing that surprised me about closing"
    ]
  }
}